<?xml version="1.0" encoding="utf-8" standalone="no"?>
<installer-gui-script minSpecVersion="1">
    <title>BitBoxBridge</title>
    <organization>ch.shiftcrypto</organization>
    <background alignment="bottomleft" file="BBBridge_icon_blue_160x125.png" scaling="none" />
    <background-darkAqua alignment="bottomleft" file="BBBridge_icon_blue_160x125.png" scaling="none" />
    <domains enable_localSystem="true"/>
    <options customize="never" require-scripts="true" rootVolumeOnly="true" />
    <!-- Define documents displayed at various steps -->
    <welcome    file="welcome.html"    mime-type="text/html" />
    <license    file="license.txt"    mime-type="text/plain" />
    <conclusion file="conclusion.html" mime-type="text/html" />
    <!-- List all component packages -->
    <pkg-ref id="ch.shiftcrypto.bitboxbridge"
             version="0"
             auth="root">bridge.pkg</pkg-ref>
    <!-- List them again here. They can now be organized
         as a hierarchy if you want. -->
    <choices-outline>
        <line choice="ch.shiftcrypto.bitboxbridge"/>
    </choices-outline>
    <!-- Define each choice above -->
    <choice
        id="ch.shiftcrypto.bitboxbridge"
        visible="false"
        title="BitBoxBridge"
        description="BitBoxBridge is something"
        start_selected="true">
      <pkg-ref id="ch.shiftcrypto.bitboxbridge"/>
    </choice>
</installer-gui-script>
